ADAFMNoiseReducer/ADAFMNoiseReducer.py
ADAFMNoiseReducer/ADAFMNoiseReducerModel.pth
ADAFMNoiseReducer/__init__.py
ADAFMNoiseReducer/utils.py
ADAFMNoiseReducer/models/SR_model.py
ADAFMNoiseReducer/models/__init__.py
ADAFMNoiseReducer/models/base_model.py
ADAFMNoiseReducer/models/networks.py
ADAFMNoiseReducer/models/modules/__init__.py
ADAFMNoiseReducer/models/modules/architecture.py
ADAFMNoiseReducer/models/modules/block.py
ADAFMNoiseReducer-1.0.2.dist-info/METADATA
ADAFMNoiseReducer-1.0.2.dist-info/WHEEL
ADAFMNoiseReducer-1.0.2.dist-info/top_level.txt
ADAFMNoiseReducer-1.0.2.dist-info/RECORD
