Metadata-Version: 2.1
Name: ADAFMNoiseReducer
Version: 1.0.2
Summary: Simple noise reducer from ADAFM architecture
Home-page: https://github.com/JeanMaximilienCadic
Author: Jean Maximilien Cadic
Author-email: j.cadic@pm.me
License: MIT
Platform: UNKNOWN
Classifier: Programming Language :: Python :: 3.6
Classifier: License :: OSI Approved :: MIT License
Requires-Python: >=3.6
Requires-Dist: gnutools-python
Requires-Dist: opencv-python (==4.4.0.44)
Requires-Dist: torch (==1.6.0)
Requires-Dist: torchvision (==0.7.0)
Requires-Dist: numpy (==1.19.1)
